ansiart/__init__.py
ansiart/ansiart.py
ansiart-1.1.0.dist-info/LICENSE
ansiart-1.1.0.dist-info/METADATA
ansiart-1.1.0.dist-info/WHEEL
ansiart-1.1.0.dist-info/top_level.txt
ansiart-1.1.0.dist-info/RECORD
