Metadata-Version: 2.1
Name: ansiart
Version: 1.1.0
Summary: This is a library that converts the image to ANSI escape sequence, outputs it to the CLI, and saves/loads into a text file.
Author-email: kokecoco <kokecoco.kw@gmail.com>
License: MIT License
Project-URL: Homepage, https://kokecoco.github.io/ansiart-docs/
Project-URL: Repository, https://github.com/Kokecoco/ansiart
Keywords: ansi,art,image,cli,terminal
Classifier: Programming Language :: Python :: 3
Classifier: License :: OSI Approved :: MIT License
Classifier: Operating System :: OS Independent
License-File: LICENSE
Requires-Dist: Pillow ==10.2.0
